[{"description":"Sample article showcasing basic code syntax and formatting for HTML elements.","permalink":"/code-syntax/","tags":[{"permalink":"/@markdown/","title":"markdown"},{"permalink":"/@css/","title":"css"},{"permalink":"/@html/","title":"html"}],"title":"Code Syntax Guide"},{"description":"Key0's description","permalink":"/key0/","tags":[{"permalink":"/@tag-i/","title":"Tag I"},{"permalink":"/@tag-ii/","title":"Tag II"}],"title":"Key0"},{"description":"Key1's description","permalink":"/key1/","tags":[{"permalink":"/@tag-i/","title":"Tag I"},{"permalink":"/@tag-ii/","title":"Tag II"},{"permalink":"/@tag-iii/","title":"Tag III"}],"title":"Key1"}]